{
  "rainforest": {"phonetic":"/ˈreɪnfɔːrɪst/","meaning":"雨林","pos":"n."},
  "explore": {"phonetic":"/ɪkˈsplɔː(r)/","meaning":"探索；探险","pos":"v."},
  "nature": {"phonetic":"/ˈneɪtʃə(r)/","meaning":"自然；天性","pos":"n."},
  "mysterious": {"phonetic":"/mɪˈstɪəriəs/","meaning":"神秘的","pos":"adj."},
  "valley": {"phonetic":"/ˈvæli/","meaning":"山谷；溪谷","pos":"n."},
  "peak": {"phonetic":"/piːk/","meaning":"山峰；最高点","pos":"n."},
  "mirror": {"phonetic":"/ˈmɪrə(r)/","meaning":"反映；反射","pos":"v."},
  "unveil": {"phonetic":"/ʌnˈveɪl/","meaning":"揭开；展露","pos":"v."},
  "identity": {"phonetic":"/aɪˈdentəti/","meaning":"身份；特征","pos":"n."},
  "stream": {"phonetic":"/striːm/","meaning":"流媒体播放；流淌","pos":"v./n."},
  "mentor": {"phonetic":"/ˈmentɔː(r)/","meaning":"导师；指导","pos":"n./v."},
  "embark": {"phonetic":"/ɪmˈbɑːk/","meaning":"着手；启程","pos":"v."},
  "expedition": {"phonetic":"/ˌekspəˈdɪʃn/","meaning":"远征；探险","pos":"n."},
  "conquer": {"phonetic":"/ˈkɒŋkə(r)/","meaning":"战胜；征服","pos":"v."},
  "documentary": {"phonetic":"/ˌdɒkjuˈmentri/","meaning":"纪录片；纪实的","pos":"n./adj."},
  "equivalent": {"phonetic":"/ɪˈkwɪvələnt/","meaning":"等同物；相等的","pos":"n./adj."},
  "ascend": {"phonetic":"/əˈsend/","meaning":"上升；攀登","pos":"v."},
  "undergo": {"phonetic":"/ˌʌndəˈɡəʊ/","meaning":"经历；接受","pos":"v."},
  "systematic": {"phonetic":"/ˌsɪstəˈmætɪk/","meaning":"系统的","pos":"adj."},
  "proactively": {"phonetic":"/prəʊˈæktɪvli/","meaning":"主动地","pos":"adv."},
  "discipline": {"phonetic":"/ˈdɪsəplɪn/","meaning":"门类；纪律","pos":"n./v."},
  "distinction": {"phonetic":"/dɪˈstɪŋkʃn/","meaning":"区别；差异","pos":"n."},
  "gear": {"phonetic":"/ɡɪə(r)/","meaning":"装备；器械","pos":"n."}
}